Metadata-Version: 2.1
Name: getopts
Version: 1.0.4
Summary: Yet another getopt library for Python
Home-page: https://github.com/markuskimius/getopt-py
Author: Mark Kim
Author-email: markuskimius+py@gmail.com
License: Apache 2.0
Keywords: getopt
Platform: UNKNOWN
